rutyva/__init__.py
rutyva/base_model.py
rutyva/from_dict_generator.py
rutyva/validation.py
rutyva-0.1.0.dist-info/LICENSE
rutyva-0.1.0.dist-info/METADATA
rutyva-0.1.0.dist-info/WHEEL
rutyva-0.1.0.dist-info/top_level.txt
rutyva-0.1.0.dist-info/RECORD
