Metadata-Version: 2.1
Name: rutyva
Version: 0.1.0
Summary: A Python library to enforce static typing at runtime
Home-page: https://github.com/guifonte/rutyva
Author: Guilherme Fontebasso
License: UNKNOWN
Platform: UNKNOWN
Classifier: Programming Language :: Python :: 3
Classifier: License :: OSI Approved :: MIT License
Classifier: Operating System :: OS Independent
Requires-Python: >=3.9
License-File: LICENSE
